codemate/__init__.py
codemate/block.py
codemate/exceptions.py
codemate/file.py
codemate/method.py
codemate/structure.py
codemate/utils.py
codemate/validator.py
codemate-0.3.0.dist-info/LICENSE
codemate-0.3.0.dist-info/WHEEL
codemate-0.3.0.dist-info/METADATA
codemate-0.3.0.dist-info/RECORD
