Metadata-Version: 2.1
Name: codemate
Version: 0.3.0
Summary: Python syntax generator based on Object-Oriented Programing, type hints, and simplicity
Home-page: https://github.com/Cyberproof/codemate
Author: Dor Abu
Author-email: dor.abu@cyberproof.com
Requires-Python: >=3.6
Classifier: Intended Audience :: Information Technology
Classifier: Intended Audience :: System Administrators
Classifier: Operating System :: OS Independent
Classifier: Programming Language :: Python :: 3
Classifier: Programming Language :: Python
Classifier: Topic :: Software Development :: Libraries :: Python Modules
Classifier: Topic :: Software Development :: Libraries
Classifier: Topic :: Software Development
Classifier: Typing :: Typed
Classifier: Intended Audience :: Developers
Classifier: License :: OSI Approved :: MIT License
Classifier: Programming Language :: Python :: 3.6
Classifier: Programming Language :: Python :: 3.7
Classifier: Programming Language :: Python :: 3.8
Classifier: Programming Language :: Python :: 3.9
Requires-Dist: black>=21.7b0,<22.0
Requires-Dist: isort[requirements_deprecated_finder,pipfile_deprecated_finder]>=5.8.0,<6.0.0
Requires-Dist: mypy==0.782 ; extra == "dev"
Requires-Dist: flake8>=3.9.2,<4.0.0 ; extra == "dev"
Requires-Dist: pre-commit>=2.12.1,<3.0.0 ; extra == "dev"
Requires-Dist: pylint>=2.8.2,<3.0.0 ; extra == "dev"
Requires-Dist: mkdocstrings>=0.15.2,<1.0.0 ; extra == "doc"
Requires-Dist: mkdocs-material>=7.2.5,<8.0.0 ; extra == "doc"
Requires-Dist: mkdocs-markdownextradata-plugin>=0.2.4,<1.0.0 ; extra == "doc"
Requires-Dist: pytest==5.4.3 ; extra == "test"
Requires-Dist: pytest-cov==2.10.0 ; extra == "test"
Requires-Dist: mypy==0.782 ; extra == "test"
Requires-Dist: flake8>=3.9.2,<4.0.0 ; extra == "test"
Requires-Dist: pylint>=2.8.2,<3.0.0 ; extra == "test"
Provides-Extra: all
Provides-Extra: dev
Provides-Extra: doc
Provides-Extra: test
